plotenv/__init__.py
plotenv/_cm.py
plotenv/plotenv.py
plotenv-0.1.2.dist-info/METADATA
plotenv-0.1.2.dist-info/RECORD
plotenv-0.1.2.dist-info/WHEEL
plotenv-0.1.2.dist-info/top_level.txt
