Metadata-Version: 2.1
Name: plotenv
Version: 0.1.2
Summary: Python plotting wrapper utilizing matplotlib and seaborn
Home-page: https://github.com/lento234/plotenv
Author: Lento Manickathan
Author-email: lento.manickathan@gmail.com
Maintainer: Lento Manickathan
Maintainer-email: lento.manickathan@gmail.com
License: GNU General Public License (GPL)
Keywords: python plotting wrapper
Platform: UNKNOWN
Classifier: Intended Audience :: Science/Research
Classifier: License :: OSI Approved :: GNU General Public License (GPL)
Classifier: Topic :: Scientific/Engineering :: Visualization
Classifier: Operating System :: POSIX
Classifier: Programming Language :: Python :: 3.6
